utopia_cli
