Metadata-Version: 2.1
Name: utopia-cli
Version: 1.1.1
Summary: Set of CLIs for managing UtopiaServer
Home-page: https://gitlab.nwmqpa.com/UtopiaServer/UtopiaInfrastructure/utopiaclis
Author: nwmqpa
Author-email: thomas.nicollet@epitech.eu
License: UNKNOWN
Platform: UNKNOWN
Classifier: Programming Language :: Python :: 3
Classifier: Operating System :: OS Independent
